PaqueteExtraOpt/__init__.py
PaqueteExtraOpt/FuncionesPrueba/FuncionesMultivariables.py
PaqueteExtraOpt/FuncionesPrueba/FuncionesUnivariables.py
PaqueteExtraOpt/FuncionesPrueba/__init__.py
PaqueteExtraOpt/MetodosMultivariables/HookeJeeves.py
PaqueteExtraOpt/MetodosMultivariables/NelderMead.py
PaqueteExtraOpt/MetodosMultivariables/Reeves.py
PaqueteExtraOpt/MetodosMultivariables/__init__.py
PaqueteExtraOpt/MetodosMultivariables/cauchy.py
PaqueteExtraOpt/MetodosMultivariables/newton.py
PaqueteExtraOpt/MetodosMultivariables/randomwalked.py
PaqueteExtraOpt/MetodosUnivariables/BusquedaDorada.py
PaqueteExtraOpt/MetodosUnivariables/Fibonacci.py
PaqueteExtraOpt/MetodosUnivariables/IntervalHalving.py
PaqueteExtraOpt/MetodosUnivariables/NewtonRaph.py
PaqueteExtraOpt/MetodosUnivariables/Secante.py
PaqueteExtraOpt/MetodosUnivariables/__init__.py
PaqueteExtraOpt/MetodosUnivariables/biseccion.py
PaqueteExtraOpt-0.2.dist-info/METADATA
PaqueteExtraOpt-0.2.dist-info/WHEEL
PaqueteExtraOpt-0.2.dist-info/top_level.txt
PaqueteExtraOpt-0.2.dist-info/RECORD
